kazoo_sasl/__init__.py
kazoo_sasl/client.py
kazoo_sasl/exceptions.py
kazoo_sasl/hosts.py
kazoo_sasl/interfaces.py
kazoo_sasl/loggingsupport.py
kazoo_sasl/python2atexit.py
kazoo_sasl/retry.py
kazoo_sasl/security.py
kazoo_sasl/version.py
kazoo_sasl/handlers/__init__.py
kazoo_sasl/handlers/eventlet.py
kazoo_sasl/handlers/gevent.py
kazoo_sasl/handlers/threading.py
kazoo_sasl/handlers/utils.py
kazoo_sasl/protocol/__init__.py
kazoo_sasl/protocol/connection.py
kazoo_sasl/protocol/paths.py
kazoo_sasl/protocol/serialization.py
kazoo_sasl/protocol/states.py
kazoo_sasl/recipe/__init__.py
kazoo_sasl/recipe/barrier.py
kazoo_sasl/recipe/cache.py
kazoo_sasl/recipe/counter.py
kazoo_sasl/recipe/election.py
kazoo_sasl/recipe/lease.py
kazoo_sasl/recipe/lock.py
kazoo_sasl/recipe/partitioner.py
kazoo_sasl/recipe/party.py
kazoo_sasl/recipe/queue.py
kazoo_sasl/recipe/watchers.py
kazoo_sasl/testing/__init__.py
kazoo_sasl/testing/common.py
kazoo_sasl/testing/harness.py
kazoo_sasl/tests/__init__.py
kazoo_sasl/tests/test_barrier.py
kazoo_sasl/tests/test_build.py
kazoo_sasl/tests/test_cache.py
kazoo_sasl/tests/test_client.py
kazoo_sasl/tests/test_connection.py
kazoo_sasl/tests/test_counter.py
kazoo_sasl/tests/test_election.py
kazoo_sasl/tests/test_eventlet_handler.py
kazoo_sasl/tests/test_exceptions.py
kazoo_sasl/tests/test_gevent_handler.py
kazoo_sasl/tests/test_hosts.py
kazoo_sasl/tests/test_interrupt.py
kazoo_sasl/tests/test_lease.py
kazoo_sasl/tests/test_lock.py
kazoo_sasl/tests/test_partitioner.py
kazoo_sasl/tests/test_party.py
kazoo_sasl/tests/test_paths.py
kazoo_sasl/tests/test_queue.py
kazoo_sasl/tests/test_retry.py
kazoo_sasl/tests/test_security.py
kazoo_sasl/tests/test_threading_handler.py
kazoo_sasl/tests/test_watchers.py
kazoo_sasl/tests/util.py
kazoo_sasl-2.6.1.dist-info/LICENSE.txt
kazoo_sasl-2.6.1.dist-info/METADATA
kazoo_sasl-2.6.1.dist-info/RECORD
kazoo_sasl-2.6.1.dist-info/WHEEL
kazoo_sasl-2.6.1.dist-info/top_level.txt
