Metadata-Version: 2.1
Name: kazoo-sasl
Version: 2.6.1
Summary: Higher Level Zookeeper Client
Home-page: https://kazoo.readthedocs.io
Author: Kazoo team
Author-email: python-zk@googlegroups.com
License: Apache 2.0
Keywords: zookeeper lock leader configuration
Platform: UNKNOWN
Classifier: Development Status :: 5 - Production/Stable
Classifier: License :: OSI Approved :: Apache Software License
Classifier: Intended Audience :: Developers
Classifier: Operating System :: OS Independent
Classifier: Programming Language :: Python
Classifier: Programming Language :: Python :: 2
Classifier: Programming Language :: Python :: 2.7
Classifier: Programming Language :: Python :: 3
Classifier: Programming Language :: Python :: 3.4
Classifier: Programming Language :: Python :: 3.5
Classifier: Programming Language :: Python :: 3.6
Classifier: Programming Language :: Python :: Implementation :: CPython
Classifier: Programming Language :: Python :: Implementation :: PyPy
Classifier: Topic :: Communications
Classifier: Topic :: System :: Distributed Computing
Classifier: Topic :: System :: Networking
Provides-Extra: test
Requires-Dist: six
Provides-Extra: test
Requires-Dist: six; extra == 'test'
Requires-Dist: coverage; extra == 'test'
Requires-Dist: mock; extra == 'test'
Requires-Dist: nose; extra == 'test'
Requires-Dist: flake8; extra == 'test'
Requires-Dist: pure-sasl; extra == 'test'
